{
  "male": [
    {
      "id": "male:sole male",
      "title": "male:sole male"
    },
    {
      "id": "male:anal",
      "title": "male:anal"
    },
    {
      "id": "male:big penis",
      "title": "male:big penis"
    },
    {
      "id": "male:dark skin",
      "title": "male:dark skin"
    },
    {
      "id": "male:muscle",
      "title": "male:muscle"
    },
    {
      "id": "male:glasses",
      "title": "male:glasses"
    },
    {
      "id": "male:dilf",
      "title": "male:dilf"
    },
    {
      "id": "male:furry",
      "title": "male:furry"
    },
    {
      "id": "male:bbm",
      "title": "male:bbm"
    },
    {
      "id": "male:tomgirl",
      "title": "male:tomgirl"
    },
    {
      "id": "male:crossdressing",
      "title": "male:crossdressing"
    },
    {
      "id": "male:schoolboy uniform",
      "title": "male:schoolboy uniform"
    },
    {
      "id": "male:gender change",
      "title": "male:gender change"
    },
    {
      "id": "male:anal intercourse",
      "title": "male:anal intercourse"
    },
    {
      "id": "male:monster",
      "title": "male:monster"
    },
    {
      "id": "male:condom",
      "title": "male:condom"
    },
    {
      "id": "male:blowjob",
      "title": "male:blowjob"
    },
    {
      "id": "male:bondage",
      "title": "male:bondage"
    },
    {
      "id": "male:bald",
      "title": "male:bald"
    },
    {
      "id": "male:virginity",
      "title": "male:virginity"
    },
    {
      "id": "male:first person perspective",
      "title": "male:first person perspective"
    },
    {
      "id": "male:teacher",
      "title": "male:teacher"
    },
    {
      "id": "male:rape",
      "title": "male:rape"
    },
    {
      "id": "male:stockings",
      "title": "male:stockings"
    },
    {
      "id": "male:group",
      "title": "male:group"
    },
    {
      "id": "male:facial hair",
      "title": "male:facial hair"
    },
    {
      "id": "male:old man",
      "title": "male:old man"
    },
    {
      "id": "male:masturbation",
      "title": "male:masturbation"
    },
    {
      "id": "male:sex toys",
      "title": "male:sex toys"
    },
    {
      "id": "male:sweating",
      "title": "male:sweating"
    },
    {
      "id": "male:harem",
      "title": "male:harem"
    },
    {
      "id": "male:dickgirl on male",
      "title": "male:dickgirl on male"
    },
    {
      "id": "male:catboy",
      "title": "male:catboy"
    },
    {
      "id": "male:nakadashi",
      "title": "male:nakadashi"
    },
    {
      "id": "male:cheating",
      "title": "male:cheating"
    },
    {
      "id": "male:gender morph",
      "title": "male:gender morph"
    },
    {
      "id": "male:prostate massage",
      "title": "male:prostate massage"
    },
    {
      "id": "male:collar",
      "title": "male:collar"
    },
    {
      "id": "male:feminization",
      "title": "male:feminization"
    },
    {
      "id": "male:dog",
      "title": "male:dog"
    },
    {
      "id": "male:transformation",
      "title": "male:transformation"
    },
    {
      "id": "male:huge penis",
      "title": "male:huge penis"
    },
    {
      "id": "male:human on furry",
      "title": "male:human on furry"
    },
    {
      "id": "male:hairy",
      "title": "male:hairy"
    },
    {
      "id": "male:military",
      "title": "male:military"
    },
    {
      "id": "male:ahegao",
      "title": "male:ahegao"
    },
    {
      "id": "male:tall man",
      "title": "male:tall man"
    },
    {
      "id": "male:exhibitionism",
      "title": "male:exhibitionism"
    },
    {
      "id": "male:demon",
      "title": "male:demon"
    },
    {
      "id": "male:masked face",
      "title": "male:masked face"
    },
    {
      "id": "male:handjob",
      "title": "male:handjob"
    },
    {
      "id": "male:dog boy",
      "title": "male:dog boy"
    },
    {
      "id": "male:pegging",
      "title": "male:pegging"
    },
    {
      "id": "male:business suit",
      "title": "male:business suit"
    },
    {
      "id": "male:horns",
      "title": "male:horns"
    },
    {
      "id": "male:big balls",
      "title": "male:big balls"
    },
    {
      "id": "male:schoolgirl uniform",
      "title": "male:schoolgirl uniform"
    },
    {
      "id": "male:smegma",
      "title": "male:smegma"
    },
    {
      "id": "male:orc",
      "title": "male:orc"
    },
    {
      "id": "male:miniguy",
      "title": "male:miniguy"
    },
    {
      "id": "male:wolf boy",
      "title": "male:wolf boy"
    }
  ],
  "female": [
    {
      "id": "female:big breasts",
      "title": "female:big breasts"
    },
    {
      "id": "female:sole female",
      "title": "female:sole female"
    },
    {
      "id": "female:stockings",
      "title": "female:stockings"
    },
    {
      "id": "female:nakadashi",
      "title": "female:nakadashi"
    },
    {
      "id": "female:blowjob",
      "title": "female:blowjob"
    },
    {
      "id": "female:schoolgirl uniform",
      "title": "female:schoolgirl uniform"
    },
    {
      "id": "female:anal",
      "title": "female:anal"
    },
    {
      "id": "female:bondage",
      "title": "female:bondage"
    },
    {
      "id": "female:rape",
      "title": "female:rape"
    },
    {
      "id": "female:ahegao",
      "title": "female:ahegao"
    },
    {
      "id": "female:milf",
      "title": "female:milf"
    },
    {
      "id": "female:glasses",
      "title": "female:glasses"
    },
    {
      "id": "female:paizuri",
      "title": "female:paizuri"
    },
    {
      "id": "female:big ass",
      "title": "female:big ass"
    },
    {
      "id": "female:twintails",
      "title": "female:twintails"
    },
    {
      "id": "female:swimsuit",
      "title": "female:swimsuit"
    },
    {
      "id": "female:sex toys",
      "title": "female:sex toys"
    },
    {
      "id": "female:futanari",
      "title": "female:futanari"
    },
    {
      "id": "female:x-ray",
      "title": "female:x-ray"
    },
    {
      "id": "female:double penetration",
      "title": "female:double penetration"
    },
    {
      "id": "female:collar",
      "title": "female:collar"
    },
    {
      "id": "female:ponytail",
      "title": "female:ponytail"
    },
    {
      "id": "female:defloration",
      "title": "female:defloration"
    },
    {
      "id": "female:yuri",
      "title": "female:yuri"
    },
    {
      "id": "female:dark skin",
      "title": "female:dark skin"
    },
    {
      "id": "female:impregnation",
      "title": "female:impregnation"
    },
    {
      "id": "female:femdom",
      "title": "female:femdom"
    },
    {
      "id": "female:gloves",
      "title": "female:gloves"
    },
    {
      "id": "female:kemonomimi",
      "title": "female:kemonomimi"
    },
    {
      "id": "female:netorare",
      "title": "female:netorare"
    },
    {
      "id": "female:bikini",
      "title": "female:bikini"
    },
    {
      "id": "female:pantyhose",
      "title": "female:pantyhose"
    },
    {
      "id": "female:furry",
      "title": "female:furry"
    },
    {
      "id": "female:hairy",
      "title": "female:hairy"
    },
    {
      "id": "female:tentacles",
      "title": "female:tentacles"
    },
    {
      "id": "female:pregnant",
      "title": "female:pregnant"
    },
    {
      "id": "female:females only",
      "title": "female:females only"
    },
    {
      "id": "female:makeup",
      "title": "female:makeup"
    },
    {
      "id": "female:huge breasts",
      "title": "female:huge breasts"
    },
    {
      "id": "female:lactation",
      "title": "female:lactation"
    },
    {
      "id": "female:lingerie",
      "title": "female:lingerie"
    },
    {
      "id": "female:very long hair",
      "title": "female:very long hair"
    },
    {
      "id": "female:sister",
      "title": "female:sister"
    },
    {
      "id": "female:cheating",
      "title": "female:cheating"
    },
    {
      "id": "female:sweating",
      "title": "female:sweating"
    },
    {
      "id": "female:mind control",
      "title": "female:mind control"
    },
    {
      "id": "female:mind break",
      "title": "female:mind break"
    },
    {
      "id": "female:masturbation",
      "title": "female:masturbation"
    },
    {
      "id": "female:exhibitionism",
      "title": "female:exhibitionism"
    },
    {
      "id": "female:handjob",
      "title": "female:handjob"
    },
    {
      "id": "female:maid",
      "title": "female:maid"
    },
    {
      "id": "female:mother",
      "title": "female:mother"
    },
    {
      "id": "female:horns",
      "title": "female:horns"
    },
    {
      "id": "female:unusual pupils",
      "title": "female:unusual pupils"
    },
    {
      "id": "female:catgirl",
      "title": "female:catgirl"
    },
    {
      "id": "female:piercing",
      "title": "female:piercing"
    },
    {
      "id": "female:garter belt",
      "title": "female:garter belt"
    },
    {
      "id": "female:bunny girl",
      "title": "female:bunny girl"
    },
    {
      "id": "female:footjob",
      "title": "female:footjob"
    },
    {
      "id": "female:urination",
      "title": "female:urination"
    },
    {
      "id": "female:kissing",
      "title": "female:kissing"
    },
    {
      "id": "female:anal intercourse",
      "title": "female:anal intercourse"
    },
    {
      "id": "female:bukkake",
      "title": "female:bukkake"
    },
    {
      "id": "female:elf",
      "title": "female:elf"
    },
    {
      "id": "female:beauty mark",
      "title": "female:beauty mark"
    },
    {
      "id": "female:small breasts",
      "title": "female:small breasts"
    },
    {
      "id": "female:demon girl",
      "title": "female:demon girl"
    },
    {
      "id": "female:cunnilingus",
      "title": "female:cunnilingus"
    },
    {
      "id": "female:gag",
      "title": "female:gag"
    },
    {
      "id": "female:shemale",
      "title": "female:shemale"
    },
    {
      "id": "female:fingering",
      "title": "female:fingering"
    },
    {
      "id": "female:big penis",
      "title": "female:big penis"
    },
    {
      "id": "female:bbw",
      "title": "female:bbw"
    },
    {
      "id": "female:tail",
      "title": "female:tail"
    },
    {
      "id": "female:stomach deformation",
      "title": "female:stomach deformation"
    },
    {
      "id": "female:inflation",
      "title": "female:inflation"
    },
    {
      "id": "female:monster girl",
      "title": "female:monster girl"
    },
    {
      "id": "female:big areolae",
      "title": "female:big areolae"
    },
    {
      "id": "female:sole dickgirl",
      "title": "female:sole dickgirl"
    },
    {
      "id": "female:blindfold",
      "title": "female:blindfold"
    },
    {
      "id": "female:thigh high boots",
      "title": "female:thigh high boots"
    },
    {
      "id": "female:latex",
      "title": "female:latex"
    },
    {
      "id": "female:filming",
      "title": "female:filming"
    },
    {
      "id": "female:tanlines",
      "title": "female:tanlines"
    },
    {
      "id": "female:leotard",
      "title": "female:leotard"
    },
    {
      "id": "female:prostitution",
      "title": "female:prostitution"
    },
    {
      "id": "female:muscle",
      "title": "female:muscle"
    },
    {
      "id": "female:harem",
      "title": "female:harem"
    },
    {
      "id": "female:bodysuit",
      "title": "female:bodysuit"
    },
    {
      "id": "female:breast expansion",
      "title": "female:breast expansion"
    },
    {
      "id": "female:drugs",
      "title": "female:drugs"
    },
    {
      "id": "female:kimono",
      "title": "female:kimono"
    },
    {
      "id": "female:teacher",
      "title": "female:teacher"
    },
    {
      "id": "female:gyaru",
      "title": "female:gyaru"
    },
    {
      "id": "female:deepthroat",
      "title": "female:deepthroat"
    },
    {
      "id": "female:wings",
      "title": "female:wings"
    },
    {
      "id": "female:bloomers",
      "title": "female:bloomers"
    },
    {
      "id": "female:blackmail",
      "title": "female:blackmail"
    },
    {
      "id": "female:transformation",
      "title": "female:transformation"
    },
    {
      "id": "female:fox girl",
      "title": "female:fox girl"
    },
    {
      "id": "female:high heels",
      "title": "female:high heels"
    },
    {
      "id": "female:hair buns",
      "title": "female:hair buns"
    },
    {
      "id": "female:rimjob",
      "title": "female:rimjob"
    },
    {
      "id": "female:eye-covering bang",
      "title": "female:eye-covering bang"
    },
    {
      "id": "female:vaginal birth",
      "title": "female:vaginal birth"
    },
    {
      "id": "female:painted nails",
      "title": "female:painted nails"
    },
    {
      "id": "female:squirting",
      "title": "female:squirting"
    },
    {
      "id": "female:corruption",
      "title": "female:corruption"
    },
    {
      "id": "female:strap-on",
      "title": "female:strap-on"
    },
    {
      "id": "female:tall girl",
      "title": "female:tall girl"
    },
    {
      "id": "female:sleeping",
      "title": "female:sleeping"
    },
    {
      "id": "female:daughter",
      "title": "female:daughter"
    },
    {
      "id": "female:big nipples",
      "title": "female:big nipples"
    },
    {
      "id": "female:school swimsuit",
      "title": "female:school swimsuit"
    },
    {
      "id": "female:shibari",
      "title": "female:shibari"
    },
    {
      "id": "female:slave",
      "title": "female:slave"
    },
    {
      "id": "female:crotch tattoo",
      "title": "female:crotch tattoo"
    },
    {
      "id": "female:nurse",
      "title": "female:nurse"
    },
    {
      "id": "female:vtuber",
      "title": "female:vtuber"
    },
    {
      "id": "female:tomboy",
      "title": "female:tomboy"
    },
    {
      "id": "female:inverted nipples",
      "title": "female:inverted nipples"
    },
    {
      "id": "female:group",
      "title": "female:group"
    },
    {
      "id": "female:hairy armpits",
      "title": "female:hairy armpits"
    },
    {
      "id": "female:dickgirl on dickgirl",
      "title": "female:dickgirl on dickgirl"
    },
    {
      "id": "female:breast feeding",
      "title": "female:breast feeding"
    },
    {
      "id": "female:penis enlargement",
      "title": "female:penis enlargement"
    },
    {
      "id": "female:tiara",
      "title": "female:tiara"
    },
    {
      "id": "female:apron",
      "title": "female:apron"
    },
    {
      "id": "female:magical girl",
      "title": "female:magical girl"
    },
    {
      "id": "female:bdsm",
      "title": "female:bdsm"
    },
    {
      "id": "female:enema",
      "title": "female:enema"
    },
    {
      "id": "female:ryona",
      "title": "female:ryona"
    },
    {
      "id": "female:spanking",
      "title": "female:spanking"
    },
    {
      "id": "female:large tattoo",
      "title": "female:large tattoo"
    },
    {
      "id": "female:miko",
      "title": "female:miko"
    },
    {
      "id": "female:vore",
      "title": "female:vore"
    },
    {
      "id": "female:fishnets",
      "title": "female:fishnets"
    },
    {
      "id": "female:blowjob face",
      "title": "female:blowjob face"
    },
    {
      "id": "female:body writing",
      "title": "female:body writing"
    },
    {
      "id": "female:cervix penetration",
      "title": "female:cervix penetration"
    },
    {
      "id": "female:hotpants",
      "title": "female:hotpants"
    },
    {
      "id": "female:torture",
      "title": "female:torture"
    },
    {
      "id": "female:giantess",
      "title": "female:giantess"
    },
    {
      "id": "female:cumflation",
      "title": "female:cumflation"
    },
    {
      "id": "female:gaping",
      "title": "female:gaping"
    },
    {
      "id": "female:halo",
      "title": "female:halo"
    },
    {
      "id": "female:humiliation",
      "title": "female:humiliation"
    },
    {
      "id": "female:pasties",
      "title": "female:pasties"
    },
    {
      "id": "female:big balls",
      "title": "female:big balls"
    },
    {
      "id": "female:exposed clothing",
      "title": "female:exposed clothing"
    },
    {
      "id": "female:nun",
      "title": "female:nun"
    },
    {
      "id": "female:nipple fuck",
      "title": "female:nipple fuck"
    },
    {
      "id": "female:facesitting",
      "title": "female:facesitting"
    },
    {
      "id": "female:bisexual",
      "title": "female:bisexual"
    },
    {
      "id": "female:business suit",
      "title": "female:business suit"
    },
    {
      "id": "female:smell",
      "title": "female:smell"
    },
    {
      "id": "female:urethra insertion",
      "title": "female:urethra insertion"
    },
    {
      "id": "female:fisting",
      "title": "female:fisting"
    },
    {
      "id": "female:witch",
      "title": "female:witch"
    },
    {
      "id": "female:focus anal",
      "title": "female:focus anal"
    },
    {
      "id": "female:hidden sex",
      "title": "female:hidden sex"
    },
    {
      "id": "female:drunk",
      "title": "female:drunk"
    },
    {
      "id": "female:male on dickgirl",
      "title": "female:male on dickgirl"
    },
    {
      "id": "female:dog girl",
      "title": "female:dog girl"
    },
    {
      "id": "female:huge penis",
      "title": "female:huge penis"
    },
    {
      "id": "female:leash",
      "title": "female:leash"
    },
    {
      "id": "female:horse girl",
      "title": "female:horse girl"
    },
    {
      "id": "female:leg lock",
      "title": "female:leg lock"
    },
    {
      "id": "female:cowgirl",
      "title": "female:cowgirl"
    },
    {
      "id": "female:pixie cut",
      "title": "female:pixie cut"
    },
    {
      "id": "female:large insertions",
      "title": "female:large insertions"
    },
    {
      "id": "female:bike shorts",
      "title": "female:bike shorts"
    },
    {
      "id": "female:gokkun",
      "title": "female:gokkun"
    },
    {
      "id": "female:solo action",
      "title": "female:solo action"
    },
    {
      "id": "female:tribadism",
      "title": "female:tribadism"
    },
    {
      "id": "female:petplay",
      "title": "female:petplay"
    },
    {
      "id": "female:milking",
      "title": "female:milking"
    },
    {
      "id": "female:chikan",
      "title": "female:chikan"
    },
    {
      "id": "female:triple penetration",
      "title": "female:triple penetration"
    },
    {
      "id": "female:body modification",
      "title": "female:body modification"
    },
    {
      "id": "female:eyepatch",
      "title": "female:eyepatch"
    },
    {
      "id": "female:freckles",
      "title": "female:freckles"
    },
    {
      "id": "female:amputee",
      "title": "female:amputee"
    },
    {
      "id": "female:robot",
      "title": "female:robot"
    },
    {
      "id": "female:cosplaying",
      "title": "female:cosplaying"
    },
    {
      "id": "female:tail plug",
      "title": "female:tail plug"
    },
    {
      "id": "female:oni",
      "title": "female:oni"
    },
    {
      "id": "female:eggs",
      "title": "female:eggs"
    },
    {
      "id": "female:oyakodon",
      "title": "female:oyakodon"
    },
    {
      "id": "female:prolapse",
      "title": "female:prolapse"
    },
    {
      "id": "female:blood",
      "title": "female:blood"
    },
    {
      "id": "female:dickgirl on female",
      "title": "female:dickgirl on female"
    },
    {
      "id": "female:chinese dress",
      "title": "female:chinese dress"
    },
    {
      "id": "female:christmas",
      "title": "female:christmas"
    },
    {
      "id": "female:possession",
      "title": "female:possession"
    },
    {
      "id": "female:detached sleeves",
      "title": "female:detached sleeves"
    },
    {
      "id": "female:eyemask",
      "title": "female:eyemask"
    },
    {
      "id": "female:wolf girl",
      "title": "female:wolf girl"
    },
    {
      "id": "female:corset",
      "title": "female:corset"
    },
    {
      "id": "female:asphyxiation",
      "title": "female:asphyxiation"
    },
    {
      "id": "female:cousin",
      "title": "female:cousin"
    }
  ],
  "mixed": [
    {
      "id": "mixed:group",
      "title": "mixed:group"
    },
    {
      "id": "mixed:ffm threesome",
      "title": "mixed:ffm threesome"
    },
    {
      "id": "mixed:mmf threesome",
      "title": "mixed:mmf threesome"
    },
    {
      "id": "mixed:inseki",
      "title": "mixed:inseki"
    }
  ],
  "other": [
    {
      "id": "other:mosaic censorship",
      "title": "other:mosaic censorship"
    },
    {
      "id": "other:full color",
      "title": "other:full color"
    },
    {
      "id": "other:multi-work series",
      "title": "other:multi-work series"
    },
    {
      "id": "other:3d",
      "title": "other:3d"
    },
    {
      "id": "other:uncensored",
      "title": "other:uncensored"
    },
    {
      "id": "other:comic",
      "title": "other:comic"
    },
    {
      "id": "other:variant set",
      "title": "other:variant set"
    },
    {
      "id": "other:western imageset",
      "title": "other:western imageset"
    },
    {
      "id": "other:tankoubon",
      "title": "other:tankoubon"
    },
    {
      "id": "other:full censorship",
      "title": "other:full censorship"
    },
    {
      "id": "other:western cg",
      "title": "other:western cg"
    },
    {
      "id": "other:story arc",
      "title": "other:story arc"
    },
    {
      "id": "other:non-nude",
      "title": "other:non-nude"
    },
    {
      "id": "other:artbook",
      "title": "other:artbook"
    },
    {
      "id": "other:no penetration",
      "title": "other:no penetration"
    },
    {
      "id": "other:nudity only",
      "title": "other:nudity only"
    },
    {
      "id": "other:anthology",
      "title": "other:anthology"
    },
    {
      "id": "other:extraneous ads",
      "title": "other:extraneous ads"
    },
    {
      "id": "other:animated",
      "title": "other:animated"
    },
    {
      "id": "other:3d imageset",
      "title": "other:3d imageset"
    },
    {
      "id": "other:sample",
      "title": "other:sample"
    },
    {
      "id": "other:incomplete",
      "title": "other:incomplete"
    },
    {
      "id": "other:non-h imageset",
      "title": "other:non-h imageset"
    },
    {
      "id": "other:themeless",
      "title": "other:themeless"
    },
    {
      "id": "other:scanmark",
      "title": "other:scanmark"
    },
    {
      "id": "other:novel",
      "title": "other:novel"
    },
    {
      "id": "other:western non-h",
      "title": "other:western non-h"
    },
    {
      "id": "other:hardcore",
      "title": "other:hardcore"
    }
  ]
}